FIFOSynchronous/sync_fifo_cnt.v
module sync_fifo_cnt #(
    parameter WIDTH = 8,
    parameter DEPTH = 16
)(
    input wire              clk,
    input wire              rst_n,
    input wire              wr_en,
    input wire [WIDTH-1:0]  din,
    input wire              rd_en,
    output reg [WIDTH-1:0]  dout,
    output wire             full,
    output wire             empty
);

    localparam ADDR_W = $clog2(DEPTH);
    localparam CNT_W  = $clog2(DEPTH + 1);

    reg [WIDTH-1:0] mem [0:DEPTH-1];
    reg [ADDR_W-1:0] wr_ptr, rd_ptr;
    reg [CNT_W-1:0]  count;


    // NEXT POINTER LOGIC
    wire [ADDR_W-1:0] wr_ptr_next = (wr_ptr == DEPTH - 1) ? 0 : wr_ptr + 1;
    wire [ADDR_W-1:0] rd_ptr_next = (rd_ptr == DEPTH - 1) ? 0 : rd_ptr + 1;

    assign empty = (count == 0);
    assign full  = (count == DEPTH);


    // MAIN LOGIC
    always @(posedge clk or negedge rst_n) begin
        if(!rst_n) begin
            wr_ptr <= 0;
            rd_ptr <= 0;
            count  <= 0;
            dout   <= 0;
        end else begin
            case ({wr_en && !full, rd_en && !empty})
                2'b10: begin // WRITE ONLY
                    mem[wr_ptr] <= din;
                    wr_ptr <= wr_ptr_next;
                    count <= count + 1;
                end
                2'b01: begin // READ ONLY
                    dout <= mem[rd_ptr];
                    rd_ptr <= rd_ptr_next;
                    count <= count - 1;
                end
                2'b11: begin // SIMULTANEOUS READ AND WRITE
                    mem[wr_ptr] <= din;
                    dout <= mem[rd_ptr];
                    wr_ptr <= wr_ptr_next;
                    rd_ptr <= rd_ptr_next;
                    count <= count;
                end
                default: begin
                    count <= count; 
                end
            endcase
        end

    end


endmodule

FIFOSynchronous/tb_sync_fifo_cnt.v
`timescale 1ns/1ps
`include "sync_fifo_cnt.v"
module tb_sync_fifo_cnt;

    // Parameters
    localparam WIDTH = 8;
    localparam DEPTH = 8;

    // DUT signals
    reg clk;
    reg rst_n;
    reg wr_en;
    reg rd_en;
    reg [WIDTH-1:0] din;

    wire [WIDTH-1:0] dout;
    wire full;
    wire empty;

    // DUT instance
    sync_fifo_cnt #(
        .WIDTH(WIDTH),
        .DEPTH(DEPTH)
    ) dut (
        .clk(clk),
        .rst_n(rst_n),
        .wr_en(wr_en),
        .din(din),
        .rd_en(rd_en),
        .dout(dout),
        .full(full),
        .empty(empty)
    );

    //-----------------------------------------
    // CLOCK
    //-----------------------------------------
    initial begin
        clk = 0;
        forever #5 clk = ~clk;   // 100MHz clock
    end

    //-----------------------------------------
    // TASK: WRITE FIFO
    //-----------------------------------------
    task write_fifo(input [WIDTH-1:0] data);
    begin
        @(posedge clk);
        wr_en = 1;
        din   = data;
        @(posedge clk);
        wr_en = 0;
        din   = 0;
    end
    endtask

    initial begin
        $dumpfile("tb_sync_fifo_cnt.vcd");
        $dumpvars(0, tb_sync_fifo_cnt);
    end

    //-----------------------------------------
    // TASK: READ FIFO
    //-----------------------------------------
    task read_fifo();
    begin
        @(posedge clk);
        rd_en = 1;
        @(posedge clk);
        rd_en = 0;
    end
    endtask

    //-----------------------------------------
    // MAIN TEST
    //-----------------------------------------
    initial begin
        // Default values
        wr_en = 0;
        rd_en = 0;
        din   = 0;

        //-------------------------------------
        // RESET
        //-------------------------------------
        rst_n = 0;
        repeat(3) @(posedge clk);
        rst_n = 1;

        $display("\n===== RESET DONE =====\n");

        //-------------------------------------
        // TEST 1: WRITE UNTIL FULL
        //-------------------------------------
        $display("===== TEST 1: WRITE UNTIL FULL =====");

        while (!full) begin
            write_fifo($urandom_range(0,255));
            #1;
            $display("WRITE din=%0d | full=%b empty=%b count≈?", 
                     dut.din, full, empty);
        end

        if (full)
            $display("FULL detected OK!\n");
        else
            $display("ERROR: FULL NOT detected!\n");

        //-------------------------------------
        // TEST 2: READ UNTIL EMPTY
        //-------------------------------------
        $display("===== TEST 2: READ UNTIL EMPTY =====");

        while (!empty) begin
            read_fifo();
            #1;
            $display("READ dout=%0d | full=%b empty=%b count≈?", 
                     dout, full, empty);
        end

        if (empty)
            $display("EMPTY detected OK!\n");

        //-------------------------------------
        // TEST 3: WRITE & READ same time
        //-------------------------------------
        $display("===== TEST 3: READ & WRITE SAME CYCLE =====");

        fork
            begin
                write_fifo(8'hAA);
                write_fifo(8'hBB);
            end
            begin
                #7; // delay cho overlap
                read_fifo();
                read_fifo();
            end
        join

        //-------------------------------------
        // FINISH
        //-------------------------------------
        $display("\n===== SIMULATION DONE =====\n");
        #20;
        $finish;
    end

endmodule

FIFOSynchronous/tb_sync_fifo_cnt.vcd
$date
	Mon Nov 17 19:28:53 2025
$end
$version
	Icarus Verilog
$end
$timescale
	1ps
$end
$scope module tb_sync_fifo_cnt $end
$var wire 1 ! full $end
$var wire 1 " empty $end
$var wire 8 # dout [7:0] $end
$var parameter 32 $ DEPTH $end
$var parameter 32 % WIDTH $end
$var reg 1 & clk $end
$var reg 8 ' din [7:0] $end
$var reg 1 ( rd_en $end
$var reg 1 ) rst_n $end
$var reg 1 * wr_en $end
$scope module dut $end
$var wire 1 & clk $end
$var wire 8 + din [7:0] $end
$var wire 1 ( rd_en $end
$var wire 1 ) rst_n $end
$var wire 1 * wr_en $end
$var wire 3 , wr_ptr_next [2:0] $end
$var wire 3 - rd_ptr_next [2:0] $end
$var wire 1 ! full $end
$var wire 1 " empty $end
$var parameter 32 . ADDR_W $end
$var parameter 32 / CNT_W $end
$var parameter 32 0 DEPTH $end
$var parameter 32 1 WIDTH $end
$var reg 4 2 count [3:0] $end
$var reg 8 3 dout [7:0] $end
$var reg 3 4 rd_ptr [2:0] $end
$var reg 3 5 wr_ptr [2:0] $end
$upscope $end
$scope task read_fifo $end
$upscope $end
$scope task write_fifo $end
$var reg 8 6 data [7:0] $end
$upscope $end
$upscope $end
$enddefinitions $end
$comment Show the parameter values. $end
$dumpall
b1000 1
b1000 0
b100 /
b11 .
b1000 %
b1000 $
$end
#0
$dumpvars
bx 6
b0 5
b0 4
b0 3
b0 2
b1 -
b1 ,
b0 +
0*
0)
0(
b0 '
0&
b0 #
1"
0!
$end
#5000
1&
#10000
0&
#15000
1&
#20000
0&
#25000
b10010010 6
1)
1&
#30000
0&
#35000
b10 ,
0"
b1 2
b1 5
b10010010 '
b10010010 +
1*
1&
#40000
0&
#45000
b0 '
b0 +
0*
1&
#46000
b1000000 6
#50000
0&
#55000
b11 ,
b10 2
b10 5
b1000000 '
b1000000 +
1*
1&
#60000
0&
#65000
b0 '
b0 +
0*
1&
#66000
b100 6
#70000
0&
#75000
b100 ,
b11 2
b11 5
b100 '
b100 +
1*
1&
#80000
0&
#85000
b0 '
b0 +
0*
1&
#86000
b110001 6
#90000
0&
#95000
b101 ,
b100 2
b100 5
b110001 '
b110001 +
1*
1&
#100000
0&
#105000
b0 '
b0 +
0*
1&
#106000
b10000110 6
#110000
0&
#115000
b110 ,
b101 2
b101 5
b10000110 '
b10000110 +
1*
1&
#120000
0&
#125000
b0 '
b0 +
0*
1&
#126000
b11000110 6
#130000
0&
#135000
b111 ,
b110 2
b110 5
b11000110 '
b11000110 +
1*
1&
#140000
0&
#145000
b0 '
b0 +
0*
1&
#146000
b110010 6
#150000
0&
#155000
b0 ,
b111 2
b111 5
b110010 '
b110010 +
1*
1&
#160000
0&
#165000
b0 '
b0 +
0*
1&
#166000
b1001 6
#170000
0&
#175000
b1 ,
1!
b1000 2
b0 5
b1001 '
b1001 +
1*
1&
#180000
0&
#185000
b0 '
b0 +
0*
1&
#190000
0&
#195000
b10 -
0!
b111 2
b1 4
b10010010 #
b10010010 3
1(
1&
#200000
0&
#205000
0(
1&
#210000
0&
#215000
b11 -
b110 2
b10 4
b1000000 #
b1000000 3
1(
1&
#220000
0&
#225000
0(
1&
#230000
0&
#235000
b100 -
b101 2
b11 4
b100 #
b100 3
1(
1&
#240000
0&
#245000
0(
1&
#250000
0&
#255000
b101 -
b100 2
b100 4
b110001 #
b110001 3
1(
1&
#260000
0&
#265000
0(
1&
#270000
0&
#275000
b110 -
b11 2
b101 4
b10000110 #
b10000110 3
1(
1&
#280000
0&
#285000
0(
1&
#290000
0&
#295000
b111 -
b10 2
b110 4
b11000110 #
b11000110 3
1(
1&
#300000
0&
#305000
0(
1&
#310000
0&
#315000
b0 -
b1 2
b111 4
b110010 #
b110010 3
1(
1&
#320000
0&
#325000
0(
1&
#330000
0&
#335000
b1 -
1"
b0 2
b0 4
b1001 #
b1001 3
1(
1&
#340000
0&
#345000
0(
1&
#346000
b10101010 6
#350000
0&
#355000
b10 ,
0"
b1 2
b1 5
b10101010 '
b10101010 +
1*
1(
1&
#360000
0&
#365000
b10111011 6
0(
b0 '
b0 +
0*
1&
#370000
0&
#375000
b10 -
b11 ,
b1 4
b10 5
b10101010 #
b10101010 3
1(
b10111011 '
b10111011 +
1*
1&
#380000
0&
#385000
b0 '
b0 +
0*
0(
1&
