FIFOSynchronous/sync_fifo_ptr.v
module sync_fifo_ptr #(
    parameter WIDTH = 8,
    parameter DEPTH = 16
)(
    input wire clk,
    input wire rst_n,
    input wire wr_en,
    input wire [WIDTH-1:0] din,
    input wire rd_en,
    output reg [WIDTH-1:0] dout,
    output wire full,
    output wire empty
);


    localparam  ADDR_W = $clog2(DEPTH);

    reg [WIDTH-1:0] mem [0:DEPTH-1];
    reg [ADDR_W-1:0] wr_ptr, rd_ptr;

    // NEXT POINTER LOGIC
    wire [ADDR_W-1:0] wr_ptr_next = (wr_ptr == DEPTH - 1) ? 0 : wr_ptr + 1;
    wire [ADDR_W-1:0] rd_ptr_next = (rd_ptr == DEPTH - 1) ? 0 : rd_ptr + 1;

    // DETECT EMPTY AND FULL CONDITIONS
    assign empty = (wr_ptr == rd_ptr);
    assign full = (wr_ptr_next == rd_ptr);

    // WRITE OPERATION
    always @(posedge clk or negedge rst_n) begin
        if (!rst_n) begin
            wr_ptr <= 0;
        end else if (wr_en && !full) begin
            mem[wr_ptr] <= din;
            wr_ptr <= wr_ptr_next;
        end
    end

    // READ OPERATION
    always @(posedge clk or negedge rst_n) begin
        if (!rst_n) begin
            rd_ptr <= 0;
            dout <= 0;
        end else if (rd_en && !empty) begin
            dout <= mem[rd_ptr];
            rd_ptr <= rd_ptr_next;
        end
    end

endmodule

FIFOSynchronous/tb_sync_fifo_ptr.v
`timescale 1ns/1ps
`include "sync_fifo_ptr.v"
module tb_sync_fifo_ptr;

    // Parameters
    localparam WIDTH = 8;
    localparam DEPTH = 8;

    // DUT Signals
    reg clk;
    reg rst_n;
    reg wr_en;
    reg rd_en;
    reg [WIDTH-1:0] din;
    wire [WIDTH-1:0] dout;
    wire full;
    wire empty;

    // Instantiate DUT
    sync_fifo_ptr #(
        .WIDTH(WIDTH),
        .DEPTH(DEPTH)
    ) dut (
        .clk(clk),
        .rst_n(rst_n),
        .wr_en(wr_en),
        .din(din),
        .rd_en(rd_en),
        .dout(dout),
        .full(full),
        .empty(empty)
    );

    //---------------------------------------
    // CLOCK GENERATION
    //---------------------------------------
    initial begin
        clk = 0;
        forever #5 clk = ~clk; // Clock = 100MHz
    end

    //---------------------------------------
    // TASK: WRITE FIFO
    //---------------------------------------
    task write_fifo(input [WIDTH-1:0] data);
    begin
        @(posedge clk);
        wr_en = 1;
        din   = data;
        @(posedge clk);
        wr_en = 0;
        din   = 0;
    end
    endtask

    //---------------------------------------
    // TASK: READ FIFO
    //---------------------------------------
    task read_fifo();
    begin
        @(posedge clk);
        rd_en = 1;
        @(posedge clk);
        rd_en = 0;
    end
    endtask

    //---------------------------------------
    // MAIN TEST SEQUENCE
    //---------------------------------------
    initial begin
        // Initial values
        wr_en = 0;
        rd_en = 0;
        din   = 0;

        // RESET
        rst_n = 0;
        repeat(3) @(posedge clk);
        rst_n = 1;
        @(posedge clk);
        $display(">> RESET DONE\n");

        //-----------------------------------
        // TEST 1: WRITE UNTIL FULL
        //-----------------------------------
        $display(">> TEST 1: WRITE UNTIL FULL");
        repeat (DEPTH-1) begin
            write_fifo($random);
            #1;
            $display("WRITE: din=%0d, full=%b, empty=%b", din, full, empty);
        end

        if (full)
            $display("FIFO FULL detected correctly\n");
        else
            $display("ERROR: FIFO should be full but is not\n");

        //-----------------------------------
        // TEST 2: READ UNTIL EMPTY
        //-----------------------------------
        $display(">> TEST 2: READ UNTIL EMPTY");
        while (!empty) begin
            read_fifo();
            #1;
            $display("READ: dout=%0d, full=%b, empty=%b", dout, full, empty);
        end

        $display("FIFO EMPTY detected correctly\n");

        //-----------------------------------
        // TEST 3: WRITE + READ SAME TIME
        //-----------------------------------
        $display(">> TEST 3: READ & WRITE same cycle");

        fork
            begin
                write_fifo(8'hAA);
                write_fifo(8'hBB);
            end
            begin
                #7; // Delay để tạo tình huống read/write overlap
                read_fifo();
                read_fifo();
            end
        join

        //-----------------------------------
        // END SIMULATION
        //-----------------------------------
        $display(">> SIM DONE");
        #20;
        $finish;
    end

    initial begin
        $dumpfile("tb_sync_fifo_ptr.vcd");
        $dumpvars(0, tb_sync_fifo_ptr);
    end

endmodule

FIFOSynchronous/tb_sync_fifo_ptr.vcd
$date
	Mon Nov 17 19:20:29 2025
$end
$version
	Icarus Verilog
$end
$timescale
	1ps
$end
$scope module tb_sync_fifo_ptr $end
$var wire 1 ! full $end
$var wire 1 " empty $end
$var wire 8 # dout [7:0] $end
$var parameter 32 $ DEPTH $end
$var parameter 32 % WIDTH $end
$var reg 1 & clk $end
$var reg 8 ' din [7:0] $end
$var reg 1 ( rd_en $end
$var reg 1 ) rst_n $end
$var reg 1 * wr_en $end
$scope module dut $end
$var wire 1 & clk $end
$var wire 8 + din [7:0] $end
$var wire 1 ( rd_en $end
$var wire 1 ) rst_n $end
$var wire 1 * wr_en $end
$var wire 3 , wr_ptr_next [2:0] $end
$var wire 3 - rd_ptr_next [2:0] $end
$var wire 1 ! full $end
$var wire 1 " empty $end
$var parameter 32 . ADDR_W $end
$var parameter 32 / DEPTH $end
$var parameter 32 0 WIDTH $end
$var reg 8 1 dout [7:0] $end
$var reg 3 2 rd_ptr [2:0] $end
$var reg 3 3 wr_ptr [2:0] $end
$upscope $end
$scope task read_fifo $end
$upscope $end
$scope task write_fifo $end
$var reg 8 4 data [7:0] $end
$upscope $end
$upscope $end
$enddefinitions $end
$comment Show the parameter values. $end
$dumpall
b1000 0
b1000 /
b11 .
b1000 %
b1000 $
$end
#0
$dumpvars
bx 4
b0 3
b0 2
b0 1
b1 -
b1 ,
b0 +
0*
0)
0(
b0 '
0&
b0 #
1"
0!
$end
#5000
1&
#10000
0&
#15000
1&
#20000
0&
#25000
1)
1&
#30000
0&
#35000
b100100 4
1&
#40000
0&
#45000
b10 ,
0"
b1 3
b100100 '
b100100 +
1*
1&
#50000
0&
#55000
b0 '
b0 +
0*
1&
#56000
b10000001 4
#60000
0&
#65000
b11 ,
b10 3
b10000001 '
b10000001 +
1*
1&
#70000
0&
#75000
b0 '
b0 +
0*
1&
#76000
b1001 4
#80000
0&
#85000
b100 ,
b11 3
b1001 '
b1001 +
1*
1&
#90000
0&
#95000
b0 '
b0 +
0*
1&
#96000
b1100011 4
#100000
0&
#105000
b101 ,
b100 3
b1100011 '
b1100011 +
1*
1&
#110000
0&
#115000
b0 '
b0 +
0*
1&
#116000
b1101 4
#120000
0&
#125000
b110 ,
b101 3
b1101 '
b1101 +
1*
1&
#130000
0&
#135000
b0 '
b0 +
0*
1&
#136000
b10001101 4
#140000
0&
#145000
b111 ,
b110 3
b10001101 '
b10001101 +
1*
1&
#150000
0&
#155000
b0 '
b0 +
0*
1&
#156000
b1100101 4
#160000
0&
#165000
1!
b0 ,
b111 3
b1100101 '
b1100101 +
1*
1&
#170000
0&
#175000
b0 '
b0 +
0*
1&
#180000
0&
#185000
b10 -
0!
b1 2
b100100 #
b100100 1
1(
1&
#190000
0&
#195000
0(
1&
#200000
0&
#205000
b11 -
b10 2
b10000001 #
b10000001 1
1(
1&
#210000
0&
#215000
0(
1&
#220000
0&
#225000
b100 -
b11 2
b1001 #
b1001 1
1(
1&
#230000
0&
#235000
0(
1&
#240000
0&
#245000
b101 -
b100 2
b1100011 #
b1100011 1
1(
1&
#250000
0&
#255000
0(
1&
#260000
0&
#265000
b110 -
b101 2
b1101 #
b1101 1
1(
1&
#270000
0&
#275000
0(
1&
#280000
0&
#285000
b111 -
b110 2
b10001101 #
b10001101 1
1(
1&
#290000
0&
#295000
0(
1&
#300000
0&
#305000
b0 -
1"
b111 2
b1100101 #
b1100101 1
1(
1&
#310000
0&
#315000
0(
1&
#316000
b10101010 4
#320000
0&
#325000
b1 ,
0"
b0 3
b10101010 '
b10101010 +
1*
1(
1&
#330000
0&
#335000
b10111011 4
0(
b0 '
b0 +
0*
1&
#340000
0&
#345000
b1 -
b10 ,
b0 2
b10101010 #
b10101010 1
b1 3
1(
b10111011 '
b10111011 +
1*
1&
#350000
0&
#355000
b0 '
b0 +
0*
0(
1&
